hayatapps_paservice_api/__init__.py
hayatapps_paservice_api/com/__init__.py
hayatapps_paservice_api/com/hayatapps/__init__.py
hayatapps_paservice_api/com/hayatapps/pa/__init__.py
hayatapps_paservice_api/com/hayatapps/pa/service/__init__.py
hayatapps_paservice_api/com/hayatapps/pa/service/model/__init__.py
hayatapps_paservice_api/com/hayatapps/pa/service/model/paservice_pb2.py
hayatapps_paservice_api/com/hayatapps/pa/service/model/paservice_pb2.pyi
hayatapps_paservice_api/com/hayatapps/pa/service/model/paservice_pb2_grpc.py
hayatapps_paservice_api/com/hayatapps/pa/service/service/__init__.py
hayatapps_paservice_api/com/hayatapps/pa/service/service/paservice_service_pb2.py
hayatapps_paservice_api/com/hayatapps/pa/service/service/paservice_service_pb2.pyi
hayatapps_paservice_api/com/hayatapps/pa/service/service/paservice_service_pb2_grpc.py
hayatapps_paservice_api-0.1.dist-info/LICENSE
hayatapps_paservice_api-0.1.dist-info/METADATA
hayatapps_paservice_api-0.1.dist-info/WHEEL
hayatapps_paservice_api-0.1.dist-info/top_level.txt
hayatapps_paservice_api-0.1.dist-info/RECORD
